isonymic/__init__.py
isonymic/cleaning.py
isonymic/indicators.py
isonymic/utils.py
isonymic/vis.py
isonymic/tests/__init__.py
isonymic/tests/test_get_isonymy.py
isonymic-0.0.9.dist-info/LICENCE.txt
isonymic-0.0.9.dist-info/METADATA
isonymic-0.0.9.dist-info/WHEEL
isonymic-0.0.9.dist-info/top_level.txt
isonymic-0.0.9.dist-info/RECORD
