Metadata-Version: 2.1
Name: isonymic
Version: 0.0.9
Summary: A simple Python package for isonymy studies from population surnames
Home-page: https://github.com/LeoMorales/isonymic-package
Author: LeoMorales
Author-email: moralesleonardo.rw@gmail.com
License: MIT
Classifier: License :: OSI Approved :: MIT License
Classifier: Programming Language :: Python :: 3.6
Classifier: Operating System :: OS Independent
Requires-Python: >=3.6
License-File: LICENCE.txt
Requires-Dist: pandas
Provides-Extra: dev
Requires-Dist: pytest >=7.0 ; extra == 'dev'
Requires-Dist: twine >=4.0.2 ; extra == 'dev'
